markpi/__init__.py
markpi/app.py
markpi/config.py
markpi/data_dantic.py
markpi/default_config/settings.yaml
markpi/funcs.py
markpi/md.py
markpi/scripts/consume.py
markpi/scripts/file1.md
markpi/scripts/file2.md
markpi/scripts/file3.md
markpi-0.1.1.dist-info/LICENSE
markpi-0.1.1.dist-info/METADATA
markpi-0.1.1.dist-info/WHEEL
markpi-0.1.1.dist-info/entry_points.txt
markpi-0.1.1.dist-info/RECORD
