Metadata-Version: 2.1
Name: markpi
Version: 0.1.1
Summary: Markdown Programmable interface
License: MIT
Author: Rishikanth Chandrasekaran
Author-email: r3chandr@ucsd.edu
Requires-Python: >=3.12,<4.0
Classifier: License :: OSI Approved :: MIT License
Classifier: Programming Language :: Python :: 3
Classifier: Programming Language :: Python :: 3.12
Requires-Dist: dynaconf (>=3.2.6,<4.0.0)
Requires-Dist: falcon (>=3.1.3,<4.0.0)
Requires-Dist: falcon-cors (>=1.1.7,<2.0.0)
Requires-Dist: fire (>=0.6.0,<0.7.0)
Requires-Dist: gunicorn (>=22.0.0,<23.0.0)
Requires-Dist: loguru (>=0.7.2,<0.8.0)
Requires-Dist: markdown (>=3.6,<4.0)
Requires-Dist: pydantic (>=2.8.2,<3.0.0)
Requires-Dist: pygments (>=2.18.0,<3.0.0)
Requires-Dist: python-markdown-math (>=0.8,<0.9)
Requires-Dist: pyyaml (>=6.0.1,<7.0.0)
Requires-Dist: regex (>=2024.7.24,<2025.0.0)
Requires-Dist: requests (>=2.32.3,<3.0.0)
Requires-Dist: tqdm (>=4.66.5,<5.0.0)
